mrtwin/__init__.py
mrtwin/_build.py
mrtwin/_prescription.py
mrtwin/_version.py
mrtwin/_brainweb/__init__.py
mrtwin/_brainweb/_base.py
mrtwin/_brainweb/_brainweb.py
mrtwin/_brainweb/_brainweb_mt.py
mrtwin/_brainweb/_brainweb_mw.py
mrtwin/_brainweb/_brainweb_mwmt.py
mrtwin/_brainweb/_segmentation.py
mrtwin/_classes/__init__.py
mrtwin/_classes/mt_model.csv
mrtwin/_classes/mw_model.csv
mrtwin/_classes/mwmt_model.csv
mrtwin/_classes/single_pool.csv
mrtwin/_fieldmap/__init__.py
mrtwin/_fieldmap/_b0_map.py
mrtwin/_fieldmap/_b1_map.py
mrtwin/_fieldmap/_birdcage.py
mrtwin/_fieldmap/_sens_map.py
mrtwin/_misc/__init__.py
mrtwin/_misc/_girf.py
mrtwin/_misc/_rigid_motion.py
mrtwin/_osf/__init__.py
mrtwin/_osf/_base.py
mrtwin/_osf/_maps.py
mrtwin/_osf/_osf.py
mrtwin/_shepplogan/__init__.py
mrtwin/_shepplogan/_base.py
mrtwin/_shepplogan/_segmentation.py
mrtwin/_shepplogan/_shepplogan.py
mrtwin/_shepplogan/_shepplogan_mt.py
mrtwin/_shepplogan/_shepplogan_mw.py
mrtwin/_shepplogan/_shepplogan_mwmt.py
mrtwin/_utils/__init__.py
mrtwin/_utils/_broadcasting.py
mrtwin/_utils/_download.py
mrtwin/_utils/_fft.py
mrtwin/_utils/_pathlib.py
mrtwin/_utils/_resample.py
mrtwin/_utils/_resize.py
mrtwin/_utils/_typing.py
mrtwin-0.1.3.dist-info/LICENSE.txt
mrtwin-0.1.3.dist-info/METADATA
mrtwin-0.1.3.dist-info/WHEEL
mrtwin-0.1.3.dist-info/top_level.txt
mrtwin-0.1.3.dist-info/RECORD
