Metadata-Version: 2.1
Name: mrtwin
Version: 0.1.3
Summary: Collection of virtual objects for numerical MR experiments.
Author-email: Matteo Cencini <matteo.cencini@gmail.com>
Project-URL: Homepage, https://github.com/INFN-MRI/mrtwin
Project-URL: Bug Reports, https://github.com/INFN-MRI/mrtwin/issues
Project-URL: Source, https://github.com/INFN-MRI/mrtwin
Keywords: brainweb,mri,download,data
Classifier: Development Status :: 3 - Alpha
Classifier: Intended Audience :: Developers
Classifier: License :: OSI Approved :: MIT License
Classifier: Programming Language :: Python :: 3.10
Classifier: Programming Language :: Python :: 3.11
Classifier: Programming Language :: Python :: 3.12
Requires-Python: >=3.10
License-File: LICENSE.txt
Requires-Dist: brainweb-dl
Requires-Dist: phantominator
Requires-Dist: osfclient
Requires-Dist: numba
Provides-Extra: dev
Requires-Dist: black; extra == "dev"
Requires-Dist: isort; extra == "dev"
Provides-Extra: doc
Requires-Dist: sphinx; extra == "doc"
Requires-Dist: pydata-sphinx-theme; extra == "doc"
Requires-Dist: sphinx-gallery; extra == "doc"
Requires-Dist: matplotlib; extra == "doc"
Provides-Extra: test
Requires-Dist: pytest; extra == "test"
Requires-Dist: pytest-black; extra == "test"
Requires-Dist: pytest-cov; extra == "test"
Requires-Dist: pytest-sugar; extra == "test"
Requires-Dist: pytest-xdist; extra == "test"
